tests/__init__.py
tests/spec_webcamd.py
webcamd/__init__.py
webcamd/__main__.py
webcamd-1.0.1.dist-info/LICENSE
webcamd-1.0.1.dist-info/METADATA
webcamd-1.0.1.dist-info/WHEEL
webcamd-1.0.1.dist-info/entry_points.txt
webcamd-1.0.1.dist-info/top_level.txt
webcamd-1.0.1.dist-info/RECORD
