Metadata-Version: 2.1
Name: webcamd
Version: 1.0.1
Summary: A minimalist service for streaming a webcam over HLS
Home-page: https://github.com/dmitri-mcguckin/webcamd
Author: Igor Maculan
Maintainer: Dmitri McGuckin
Maintainer-email: hello@dmitrimcguckin.com
License: GPL-3.0
Project-URL: Documentation, https://github.com/dmitri-mcguckin/webcamd/blob/main/README.md
Project-URL: Bug Tracking, https://github.com/dmitri-mcguckin/webcamd/issues
Platform: UNKNOWN
Classifier: Programming Language :: Python :: 3
Classifier: License :: OSI Approved :: GNU General Public License v3 (GPLv3)
Classifier: Operating System :: OS Independent
Classifier: Topic :: Scientific/Engineering :: Information Analysis
Classifier: Topic :: Software Development :: User Interfaces
Classifier: Topic :: System :: Monitoring
Classifier: Topic :: System :: Networking :: Monitoring :: Hardware Watchdog
Requires-Python: >=3.9.0
License-File: LICENSE
Requires-Dist: opencv-python (==4.5.3.56)
Requires-Dist: PIL-Tools (==1.1.0)
Provides-Extra: dev
Requires-Dist: setuptools ; extra == 'dev'
Requires-Dist: wheel ; extra == 'dev'
Requires-Dist: flake8 ; extra == 'dev'
Requires-Dist: twine ; extra == 'dev'
Requires-Dist: sphinx ; extra == 'dev'
Requires-Dist: sphinx-rtd-theme ; extra == 'dev'
